pytrail/__init__.py
pytrail/exceptions.py
pytrail/models.py
tests/__init__.py
tests/pytrailTest.py
pytrail-0.1.0.dist-info/LICENSE
pytrail-0.1.0.dist-info/METADATA
pytrail-0.1.0.dist-info/WHEEL
pytrail-0.1.0.dist-info/top_level.txt
pytrail-0.1.0.dist-info/RECORD
