Metadata-Version: 2.1
Name: pytrail
Version: 0.1.0
Summary: The pytrail module simplifies the process of fetching movie trailers programmatically. It offers a user-friendly interface to search for and retrieve the latest trailers for a wide range of movies. Integrate this module into your projects to effortlessly access and showcase movie trailers, enhancing your movie-related applications and websites.
Home-page: https://www.github.com/new92/pytrail
Author: new92
Author-email: new92github@gmail.com
Maintainer: new92
Maintainer-email: new92github@gmail.com
License: MIT
Project-URL: Github Repository, https://github.com/new92/pytrail
Keywords: python movies trailer cinema
Classifier: License :: OSI Approved :: MIT License
Classifier: Programming Language :: Python :: 3
Classifier: Programming Language :: Python :: 3.6
Classifier: Programming Language :: Python :: 3.7
Classifier: Programming Language :: Python :: 3.8
Classifier: Programming Language :: Python :: 3.9
Classifier: Programming Language :: Python :: 3.10
Classifier: Programming Language :: Python :: 3.11
Requires-Python: >=3.6
License-File: LICENSE
Requires-Dist: requests
